compress_gpt/__init__.py
compress_gpt/compress.py
compress_gpt/langchain/__init__.py
compress_gpt/langchain/prompt.py
compress_gpt/prompts/__init__.py
compress_gpt/prompts/compare_prompts.py
compress_gpt/prompts/compress_chunks.py
compress_gpt/prompts/decompress.py
compress_gpt/prompts/diff_prompts.py
compress_gpt/prompts/fix.py
compress_gpt/prompts/fix_json.py
compress_gpt/prompts/identify_format.py
compress_gpt/prompts/identify_static.py
compress_gpt/prompts/output_parser.py
compress_gpt/tests/__init__.py
compress_gpt/tests/test_compress.py
compress_gpt/utils.py
compress_gpt-0.1.2.dist-info/METADATA
compress_gpt-0.1.2.dist-info/WHEEL
compress_gpt-0.1.2.dist-info/RECORD
