Metadata-Version: 2.1
Name: compress-gpt
Version: 0.1.2
Summary: Self-extracting GPT prompts for ~70% token savings.
License: MIT
Author: Yasyf Mohamedali
Author-email: yasyfm@gmail.com
Requires-Python: >=3.10,<4.0
Classifier: License :: OSI Approved :: MIT License
Classifier: Programming Language :: Python :: 3
Classifier: Programming Language :: Python :: 3.10
Classifier: Programming Language :: Python :: 3.11
Requires-Dist: aiocache (>=0.12.0,<0.13.0)
Requires-Dist: dill (>=0.3.6,<0.4.0)
Requires-Dist: dirtyjson (>=1.0.8,<2.0.0)
Requires-Dist: hiredis (>=2.2.2,<3.0.0)
Requires-Dist: jinja2 (>=3.1.2,<4.0.0)
Requires-Dist: langchain (>=0.0.132,<0.0.133)
Requires-Dist: nest-asyncio (>=1.5.6,<2.0.0)
Requires-Dist: nltk (>=3.8.1,<4.0.0)
Requires-Dist: openai (>=0.27.4,<0.28.0)
Requires-Dist: pydantic (>=1.10.7,<2.0.0)
Requires-Dist: redis (>=4.5.4,<5.0.0)
Requires-Dist: rich (>=13.3.3,<14.0.0)
Requires-Dist: tiktoken (>=0.3.3,<0.4.0)
